Workbook

Sheet Исходные_данные
A1: Параметр | B1: Значение | C1: Ед. изм. | D1: Статус данных | E1: Пояснение
A2: Кадровых событий в демонстрационном наборе | B2: 11 | C2: событий | D2: Учебные данные; не замер потока предприятия | E2: 11 событий — исходный демонстрационный набор. Экстраполяция на год является допущением модели.
A3: Рабочих дней в контрольном периоде | B3: 20 | C3: дней | D3: Сценарное допущение | E3: 20 рабочих дней — условная длительность расчётного периода.
A4: Рабочих дней в году | B4: 247 | C4: дней | D4: Сценарное допущение | E4: 247 дней — параметр модели, не подтверждённый производственный календарь.
A5: Кадровик: расчетная стоимость часа | B5: 550 | C5: руб./ч | D5: Сценарное допущение | E5: Не является фактической зарплатой сотрудника организации
A6: Оператор уведомлений: стоимость часа | B6: 500 | C6: руб./ч | D6: Сценарное допущение | E6: Расчетная полная стоимость рабочего часа
A7: Руководитель: стоимость часа | B7: 900 | C7: руб./ч | D7: Сценарное допущение | E7: Расчетная полная стоимость рабочего часа
A8: Бухгалтерия: стоимость часа | B8: 650 | C8: руб./ч | D8: Сценарное допущение | E8: Расчетная полная стоимость рабочего часа
A9: Месячная экономия времени на сводной отчетности | B9: 2 | C9: ч/мес | D9: Сценарное допущение | E9: За счет отчетов СКД вместо ручной сверки
A10: Расчетная ставка для отчетности | B10: 550 | C10: руб./ч | D10: Сценарное допущение | E10: Ставка кадровика для расчета экономии отчетного времени
A11: Годовые эксплуатационные затраты | B11: 8000 | C11: руб./год | D11: Сценарное допущение | E11: Резерв на сопровождение, обновления и контрольные проверки
A12: Горизонт оценки | B12: 3 | C12: года | D12: Сценарное допущение | E12: Для расчета накопленного эффекта и NPV
A13: Ставка дисконтирования | B13: 0.12 | C13: доля | D13: Сценарное допущение | E13: Применяется для учебной оценки NPV
... A15: Средняя трудоемкость одной доработки AS IS | B15: 25 | C15: мин | D15: Сценарное допущение | E15: Дополнительная ручная сверка/повтор
A17: Расчетный показатель | B17: Значение
A18: Прогноз событий в год | B18: =B2/B3*B4 -> 135.85
A19: Событий в месяц | B19: =B18/12 -> 11.320833

Sheet Трудоемкость_ASIS
A1: Операция | B1: Роль | C1: Минут на событие | D1: Стоимость часа | E1: Стоимость операции | F1: Доля времени | G1: Комментарий
A2: Проверка основания и данных | B2: Кадровик | C2: 10 | D2: =Исходные_данные!$B$5 -> 550 | E2: =C2/60*D2 -> 91.666667 | F2: =C2/$D$10 -> 0.22222222 | G2: Ручная проверка исходных сведений
A3: Ручное определение получателей | B3: Кадровик | C3: 8 | D3: =Исходные_данные!$B$5 -> 550 | E3: =C3/60*D3 -> 73.333333 | F3: =C3/$D$10 -> 0.17777778 | G3: По спискам/контактным данным
A4: Подготовка текста уведомления | B4: Кадровик | C4: 10 | D4: =Исходные_данные!$B$5 -> 550 | E4: =C4/60*D4 -> 91.666667 | F4: =C4/$D$10 -> 0.22222222 | G4: Отдельное формирование текста
A5: Отправка и фиксация результата | B5: Оператор уведомлений | C5: 8 | D5: =Исходные_данные!$B$6 -> 500 | E5: =C5/60*D5 -> 66.666667 | F5: =C5/$D$10 -> 0.17777778 | G5: Ручная отправка и отметка
A6: Контроль статуса/повтор | B6: Оператор уведомлений | C6: 4 | D6: =Исходные_данные!$B$6 -> 500 | E6: =C6/60*D6 -> 33.333333 | F6: =C6/$D$10 -> 0.088888889 | G6: Ручной контроль результата
A7: Согласование/просмотр | B7: Руководитель | C7: 3 | D7: =Исходные_данные!$B$7 -> 900 | E7: =C7/60*D7 -> 45 | F7: =C7/$D$10 -> 0.066666667 | G7: Доля времени на один случай
A8: Финансово значимое уведомление | B8: Бухгалтерия | C8: 2 | D8: =Исходные_данные!$B$8 -> 650 | E8: =C8/60*D8 -> 21.666667 | F8: =C8/$D$10 -> 0.044444444 | G8: Доля времени на один случай
C10: Итого минут на событие | D10: =SUM(C2:C8) -> 45
C11: Итого часов на событие | D11: =D10/60 -> 0.75
C12: Итого стоимость на событие | D12: =SUM(E2:E8) -> 423.33333

Sheet Трудоемкость_TOBE
A1: Операция | B1: Роль | C1: Минут на событие | D1: Стоимость часа | E1: Стоимость операции | F1: Доля времени | G1: Комментарий
A2: Ввод и проверка исходных данных | B2: Кадровик | C2: 10 | D2: =Исходные_данные!$B$5 -> 550 | E2: =C2/60*D2 -> 91.666667 | F2: =C2/$D$9 -> 0.66666667 | G2: Основной ручной ввод сохраняется
A3: Автоматический подбор получателей | B3: Кадровик | C3: 0.5 | D3: =Исходные_данные!$B$5 -> 550 | E3: =C3/60*D3 -> 4.5833333 | F3: =C3/$D$9 -> 0.033333333 | G3: По правилу рассылки
A4: Формирование подготовленных уведомлений | B4: Кадровик | C4: 0.5 | D4: =Исходные_данные!$B$5 -> 550 | E4: =C4/60*D4 -> 4.5833333 | F4: =C4/$D$9 -> 0.033333333 | G4: Автоматически при проведении
A5: Контроль результатов/ошибок | B5: Оператор уведомлений | C5: 2 | D5: =Исходные_данные!$B$6 -> 500 | E5: =C5/60*D5 -> 16.666667 | F5: =C5/$D$9 -> 0.13333333 | G5: По регистрам и отчетам
A6: Просмотр результата | B6: Руководитель | C6: 1 | D6: =Исходные_данные!$B$7 -> 900 | E6: =C6/60*D6 -> 15 | F6: =C6/$D$9 -> 0.066666667 | G6: Через отчет
A7: Контроль финансового изменения | B7: Бухгалтерия | C7: 1 | D7: =Исходные_данные!$B$8 -> 650 | E7: =C7/60*D7 -> 10.833333 | F7: =C7/$D$9 -> 0.066666667 | G7: Через уведомление/отчет
C9: Итого минут на событие | D9: =SUM(C2:C7) -> 15
C10: Итого часов на событие | D10: =D9/60 -> 0.25
C11: Итого стоимость на событие | D11: =SUM(E2:E7) -> 143.33333

Sheet Стоимость_разработки
A1: Этап | B1: Трудоемкость, ч | C1: Ставка, руб./ч | D1: Стоимость | E1: Статус | F1: Комментарий
A2: Анализ и постановка задачи | B2: 8 | C2: 600 | D2: =B2*C2 -> 4800 | E2: сценарное | F2: Аналитическая часть и требования
A3: Проектирование процесса и данных | B3: 12 | C3: 650 | D3: =B3*C3 -> 7800 | E3: сценарное | F3: AS IS/TO BE, архитектура, модели данных
A4: Разработка конфигурации 1С | B4: 28 | C4: 700 | D4: =B4*C4 -> 19600 | E4: сценарное | F4: Объекты, модули, СКД, роли, бизнес-процесс
A5: Тестирование и исправления | B5: 10 | C5: 600 | D5: =B5*C5 -> 6000 | E5: сценарное | F5: Функциональные и регрессионные проверки
A6: Документирование и развертывание | B6: 7 | C6: 550 | D6: =B6*C6 -> 3850 | E6: сценарное | F6: README, инструкции, поставка
A8: Показатель | B8: Значение
A9: Итого стоимость разработки | B9: =SUM(D2:D6) -> 42050

Sheet Эффективность
A1: Показатель | B1: Формула/основание | C1: Значение | D1: Ед. изм.
A2: Прогноз кадровых изменений в год | B2: 11 / 20 рабочих дней × 247 дней | C2: =Исходные_данные!B18 -> 135.85 | D2: событий/год
A3: Экономия времени на событие | B3: AS IS - TO BE | C3: =Трудоемкость_ASIS!D10-Трудоемкость_TOBE!D9 -> 30 | D3: мин
A4: Экономия стоимости труда на событие | B4: AS IS - TO BE | C4: =Трудоемкость_ASIS!D12-Трудоемкость_TOBE!D11 -> 280 | D4: руб./событие
A5: Годовая экономия по обработке событий | B5: события × экономия/событие | C5: =C2*C4 -> 38038 | D5: руб./год
A6: Годовая экономия на отчетности | B6: 2 ч/мес × 12 × ставка | C6: =Исходные_данные!B9*12*Исходные_данные!B10 -> 13200 | D6: руб./год
A7: Избежанные затраты на ручные доработки | B7: частота × трудоемкость × ставка | C7: =C2*Исходные_данные!B14*Исходные_данные!B15/60*Исходные_данные!B5 -> 2490.5833 | D7: руб./год
A8: Валовой годовой эффект | B8: сумма трех эффектов | C8: =SUM(C5:C7) -> 53728.583 | D8: руб./год
A9: Эксплуатационные затраты | B9: из исходных данных | C9: =Исходные_данные!B11 -> 8000 | D9: руб./год
A10: Чистый годовой эффект | B10: валовой эффект - эксплуатация | C10: =C8-C9 -> 45728.583 | D10: руб./год
A11: Инвестиции в разработку | B11: смета разработки | C11: =Стоимость_разработки!B9 -> 42050 | D11: руб.
A12: Срок окупаемости | B12: инвестиции / чистый эффект × 12 | C12: =IF(C10>0,C11/C10*12,"Не окупается") -> 11.034674 | D12: мес.
A13: Коэффициент годового эффекта к инвестициям | B13: чистый годовой эффект / инвестиции | C13: =C10/C11 -> 1.0874812 | D13: коэфф.
A14: ROI первого года | B14: (чистый годовой эффект - инвестиции) / инвестиции | C14: =(C10-C11)/C11 -> 0.087481173 | D14: %

Sheet Денежный_поток
A1: Год | B1: Инвестиции | C1: Чистый эффект | D1: Денежный поток | E1: Коэффициент дисконтирования | F1: Дисконтированный поток
A2: 0 | B2: =-Эффективность!C11 -> -42050 | C2: 0 | D2: =B2+C2 -> -42050 | E2: 1 | F2: =D2*E2 -> -42050
A3: 1 | B3: 0 | C3: =Эффективность!C10 -> 45728.583 | D3: =B3+C3 -> 45728.583 | E3: =1/(1+Исходные_данные!$B$13)^A3 -> 0.89285714 | F3: =D3*E3 -> 40829.092
A4: 2 | B4: 0 | C4: =Эффективность!C10 -> 45728.583 | D4: =B4+C4 -> 45728.583 | E4: =1/(1+Исходные_данные!$B$13)^A4 -> 0.79719388 | F4: =D4*E4 -> 36454.547
A5: 3 | B5: 0 | C5: =Эффективность!C10 -> 45728.583 | D5: =B5+C5 -> 45728.583 | E5: =1/(1+Исходные_данные!$B$13)^A5 -> 0.71178025 | F5: =D5*E5 -> 32548.702
A7: Показатель | B7: Значение
A8: NPV за 3 года | B8: =SUM(F2:F5) -> 67782.341
A9: Индекс доходности (PI) | B9: =SUM(F3:F5)/ABS(F2) -> 2.6119463

Sheet Чувствительность
A1: Сценарий | B1: Событий в год | C1: Экономия на обработке | D1: Чистый годовой эффект | E1: Окупаемость, мес.
A2: Консервативный | B2: 100 | C2: =B2*Эффективность!C4 -> 28000 | D2: =C2+Эффективность!C6+(B2*Исходные_данные!B14*Исходные_данные!B15/60*Исходные_данные!B5)-Эффективность!C9 -> 35033.333 | E2: =Эффективность!C11/D2*12 -> 14.403425
A3: Базовый | B3: =Эффективность!C2 -> 135.85 | C3: =B3*Эффективность!C4 -> 38038 | D3: =C3+Эффективность!C6+(B3*Исходные_данные!B14*Исходные_данные!B15/60*Исходные_данные!B5)-Эффективность!C9 -> 45728.583 | E3: =Эффективность!C11/D3*12 -> 11.034674
A4: Интенсивный | B4: 170 | C4: =B4*Эффективность!C4 -> 47600 | D4: =C4+Эффективность!C6+(B4*Исходные_данные!B14*Исходные_данные!B15/60*Исходные_данные!B5)-Эффективность!C9 -> 55916.667 | E4: =Эффективность!C11/D4*12 -> 9.0241431

Sheet Пояснения
A1: Пункт | B1: Содержание
A2: 1 | B2: 11 событий — набор примеров из материалов практики за 18.05–14.06.2026. Это не измерение производственного потока.
A3: 2 | B3: Стоимости рабочего часа, длительности операций, эксплуатационные затраты, ставка дисконтирования и доля ручных доработок являются сценарными расчетными параметрами учебной модели.
A4: 3 | B4: Модель не утверждает фактическую зарплату работников ООО «Кадровые технологии» и не выдает демонстрационную организацию за источник бухгалтерских данных.
A5: 4 | B5: 135,85 события в год — расчётный сценарий по условной интенсивности 11 событий за 20 дней; 247 дней также заданы как допущение.
A6: 5 | B6: Эффект складывается из экономии времени обработки одного события, экономии времени на сводной отчетности и расчетных затрат на устранение ручных ошибок.
A7: 6 | B7: Для оценки внедрения нужны замеры ручного процесса, статистика кадровых событий и утверждённые затраты. Структура формул позволяет заменить исходные параметры.
A9: Основание расчёта | B9: Времена, ставки, интенсивность, затраты и частота ошибок являются сценарными оценками.
A10: Данные практики | B10: Наличие 11 примеров не доказывает, что предприятие обрабатывает именно 11 событий за 20 дней.
A11: Испытания версии 0.12.1 | B11: 60 кадровых событий и 120 уведомлений проверяют работоспособность программы. Их количество не используется как прогноз потока предприятия.
A12: Область применения | B12: Учебный прототип. Экономическая модель не подтверждает промышленное внедрение.
A13: Диаграммы | B13: Три диаграммы исходной книги переработаны и связаны с ячейками листа Графики; данные и формулы сохранены.
A14: Источник | B14: Исходная книга economic_model_v06_SOURCE.xlsx из архива автора. Сохранены формулы и три редактируемые диаграммы Excel.

Sheet Графики
A1: Показатель | B1: До автоматизации | C1: Проектный сценарий
A2: Минут на событие | B2: =Трудоемкость_ASIS!D10 -> 45 | C2: =Трудоемкость_TOBE!D9 -> 15
A3: Стоимость труда на событие | B3: =Трудоемкость_ASIS!D12 -> 423.33333 | C3: =Трудоемкость_TOBE!D11 -> 143.33333
A4: Ручных минут кадровика/оператора | B4: =SUM(Трудоемкость_ASIS!C2:C6) -> 40 | C4: =SUM(Трудоемкость_TOBE!C2:C5) -> 13
A5: Автоматизированная проверка исключений | B5: 0 | C5: 4
A8: Компонент эффекта | B8: руб./год
A9: Обработка событий | B9: =Эффективность!C5 -> 38038
A10: Подготовка отчётов | B10: =Эффективность!C6 -> 13200
A11: Исправление ошибок | B11: =Эффективность!C7 -> 2490.5833
A12: Сопровождение | B12: =-Эффективность!C9 -> -8000
A13: Чистый годовой эффект | B13: =Эффективность!C10 -> 45728.583
A16: Год | B16: Денежный поток | C16: Накопленный поток | D16: Дисконтированный поток
A17: 0 | B17: =Денежный_поток!D2 -> -42050 | C17: =B17 -> -42050 | D17: =Денежный_поток!F2 -> -42050
A18: 1 | B18: =Денежный_поток!D3 -> 45728.583 | C18: =C17+B18 -> 3678.5833 | D18: =Денежный_поток!F3 -> 40829.092
A19: 2 | B19: =Денежный_поток!D4 -> 45728.583 | C19: =C18+B19 -> 49407.167 | D19: =Денежный_поток!F4 -> 36454.547
A20: 3 | B20: =Денежный_поток!D5 -> 45728.583 | C20: =C19+B20 -> 95135.75 | D20: =Денежный_поток!F5 -> 32548.702
A22: Расчётный сценарий — не результаты испытаний.
A24: Измените исходные параметры и времена на соответствующих листах. Диаграммы используют формулы, а не вручную введённые итоговые значения.
